workout/__init__.py
workout/__main__.py
workout/_version.py
git_workout-0.0.0.dist-info/LICENSE
git_workout-0.0.0.dist-info/METADATA
git_workout-0.0.0.dist-info/WHEEL
git_workout-0.0.0.dist-info/entry_points.txt
git_workout-0.0.0.dist-info/top_level.txt
git_workout-0.0.0.dist-info/RECORD
