Metadata-Version: 2.1
Name: git-workout
Version: 0.0.0
Summary: Prove that you only work on your own stuff out of hours.
Home-page: https://github.com/judy2k/git-workout
Author: Mark Smith
Author-email: judy@judy.co.uk
License: MIT
Platform: UNKNOWN
Classifier: Programming Language :: Python :: 3
Classifier: License :: OSI Approved :: MIT License
Classifier: Operating System :: OS Independent
Requires-Python: >=3.6
Requires-Dist: Click (~=7.0)
Requires-Dist: gitpython (~=2.1.11)
